{"P21": {"labels": ["\u9510\u6377\u4ea4\u6362\u673a"], "postTitle": "\u9510\u6377\u8bbe\u5907-\u6545\u969c\u6392\u67e5\u5b9d\u5178", "postUrl": "post/rui-jie-she-bei---gu-zhang-pai-cha-bao-dian.html", "createdDate": "2024-06-19", "dateLabelColor": "#bc4c00"}, "P20": {"labels": ["\u9632\u706b\u5899"], "postTitle": "\u73b0\u7f51\u5185\u6709\u9632\u706b\u5899\u5bfc\u81f4\u89c6\u9891\u4f1a\u8bae\u53c2\u4f1a\u6210\u5458\u5165\u4f1a\u65f6\u65e0\u89c4\u5f8b\u6389\u7ebf\u89e3\u51b3\u65b9\u6848", "postUrl": "post/xian-wang-nei-you-fang-huo-qiang-dao-zhi-shi-pin-hui-yi-can-hui-cheng-yuan-ru-hui-shi-wu-gui-lv-diao-xian-jie-jue-fang-an.html", "createdDate": "2024-06-05", "dateLabelColor": "#bc4c00"}, "P19": {"labels": ["\u51dd\u601d"], "postTitle": "\u786c\u76d8\u5206\u533a\u4e0e\u6302\u8f7d(\u51dd\u601d)", "postUrl": "post/ying-pan-fen-qu-yu-gua-zai-%28-ning-si-%29.html", "createdDate": "2024-04-10", "dateLabelColor": "#bc4c00"}, "P18": {"labels": ["\u534e\u4e3a"], "postTitle": "\u534e\u4e3a\u4ea4\u6362\u673aor\u8def\u7531\u5668\u5347\u7ea7", "postUrl": "post/hua-wei-jiao-huan-ji-or-lu-you-qi-sheng-ji.html", "createdDate": "2024-04-08", "dateLabelColor": "#bc4c00"}, "P17": {"labels": ["\u9510\u6377\u7ec8\u7aef7800-1000"], "postTitle": "CT7800-1000 V5.0 \u5b89\u88c5WIN7", "postUrl": "post/CT7800-1000%20V5.0%20-an-zhuang-WIN7.html", "createdDate": "2024-04-04", "dateLabelColor": "#bc4c00"}, "P16": {"labels": ["\u4e2d\u5174"], "postTitle": "\u4e2d\u5174\u8def\u7531\u5668\u89e3\u9664ARP\u7ed1\u5b9a", "postUrl": "post/zhong-xing-lu-you-qi-jie-chu-ARP-bang-ding.html", "createdDate": "2024-04-04", "dateLabelColor": "#bc4c00"}, "P15": {"labels": ["\u9e92\u9e9fV10\u7cfb\u5217"], "postTitle": "\u94f6\u6cb3\u9e92\u9e9f\u65e0\u6cd5\u8fdb\u5165root\u63d0\u793a\u6ca1\u6709\u90a3\u4e2a\u6587\u4ef6\u6216\u76ee\u5f55", "postUrl": "post/yin-he-qi-lin-wu-fa-jin-ru-root-ti-shi-mei-you-na-ge-wen-jian-huo-mu-lu.html", "createdDate": "2024-03-27", "dateLabelColor": "#bc4c00"}, "P14": {"labels": ["\u51dd\u601d"], "postTitle": "\u51dd\u601d\u7cfb\u7edf\u6dfb\u52a0\u8def\u7531", "postUrl": "post/ning-si-xi-tong-tian-jia-lu-you.html", "createdDate": "2024-03-27", "dateLabelColor": "#bc4c00"}, "P11": {"labels": ["\u7cfb\u7edf\u4e0e\u8f6f\u4ef6"], "postTitle": "\u5de5\u4f5c\u6240\u4f7f\u7528\u7cfb\u7edf\u955c\u50cf\u4ee5\u53ca\u8f6f\u4ef6\u4e0b\u8f7d", "postUrl": "post/gong-zuo-suo-shi-yong-xi-tong-jing-xiang-yi-ji-ruan-jian-xia-zai.html", "createdDate": "2024-03-25", "dateLabelColor": "#bc4c00"}, "P10": {"labels": ["\u9510\u6377\u4ea4\u6362\u673a"], "postTitle": "\u9510\u6377\u4ea4\u6362\u673a\u4ea4\u6362\u8fbe\u4eba", "postUrl": "post/rui-jie-jiao-huan-ji-jiao-huan-da-ren.html", "createdDate": "2024-03-25", "dateLabelColor": "#bc4c00"}, "P9": {"labels": ["\u9e92\u9e9fV3.3"], "postTitle": "\u9e92\u9e9fV3.3\u6587\u672c\u4e71\u7801\u95ee\u9898", "postUrl": "post/qi-lin-V3.3-wen-ben-luan-ma-wen-ti.html", "createdDate": "2024-03-25", "dateLabelColor": "#bc4c00"}, "P8": {"labels": ["\u9e92\u9e9fV3.3"], "postTitle": "\u786c\u76d8\u5206\u533a\u4e0e\u6302\u8f7d(\u9e92\u9e9f\u7cfb\u7edf)", "postUrl": "post/ying-pan-fen-qu-yu-gua-zai-%28-qi-lin-xi-tong-%29.html", "createdDate": "2024-03-25", "dateLabelColor": "#bc4c00"}, "P7": {"labels": ["\u51dd\u601d"], "postTitle": "\u51dd\u601d80\u5b89\u88c5NVIDIA\u663e\u5361\u9a71\u52a8", "postUrl": "post/ning-si-80-an-zhuang-NVIDIA-xian-qia-qu-dong.html", "createdDate": "2024-03-25", "dateLabelColor": "#bc4c00"}, "P6": {"labels": ["Python"], "postTitle": "LinuxU\u76d8\u65e0\u6cd5\u8bfb\u53d6\uff0c\u901a\u8fc7python\u8fdb\u884chttp\u6570\u636e\u4e92\u4f20", "postUrl": "post/LinuxU-pan-wu-fa-du-qu-%EF%BC%8C-tong-guo-python-jin-xing-http-shu-ju-hu-chuan.html", "createdDate": "2024-03-25", "dateLabelColor": "#bc4c00"}, "P5": {"labels": ["\u536b\u58eb\u901a\u7eb5\u5411\u52a0\u5bc6"], "postTitle": "\u536b\u58eb\u901a\u5fae\u7eb5\u5411\u6062\u590d\u51fa\u5382\u8bbe\u7f6e", "postUrl": "post/wei-shi-tong-wei-zong-xiang-hui-fu-chu-chang-she-zhi.html", "createdDate": "2024-03-25", "dateLabelColor": "#bc4c00"}, "P4": {"labels": ["\u7edf\u4fe1UOS"], "postTitle": "UOS\u9000\u51fa\u5f00\u53d1\u8005\u6a21\u5f0f", "postUrl": "post/UOS-tui-chu-kai-fa-zhe-mo-shi.html", "createdDate": "2024-03-25", "dateLabelColor": "#bc4c00"}, "P3": {"labels": ["\u9e92\u9e9fV10\u7cfb\u5217"], "postTitle": "\u9e92\u9e9fv10-SP1_2203\u7248\u672c\u5b89\u88c5\u82f1\u4f1f\u8fbe\u9a71\u52a8", "postUrl": "post/qi-lin-v10-SP1_2203-ban-ben-an-zhuang-ying-wei-da-qu-dong.html", "createdDate": "2024-03-25", "dateLabelColor": "#bc4c00"}, "labelColorDict": {"about": "#724BF4", "link": "#F03CE9", "Python": "#FBCA04", "\u4e2d\u5174": "#1D76DB", "\u51dd\u601d": "#B60205", "\u534e\u4e3a": "#E91E1B", "\u536b\u58eb\u901a\u7eb5\u5411\u52a0\u5bc6": "#C5DEF5", "\u7cfb\u7edf\u4e0e\u8f6f\u4ef6": "#E99695", "\u7edf\u4fe1UOS": "#5319E7", "\u9510\u6377\u4ea4\u6362\u673a": "#D93F0B", "\u9510\u6377\u7ec8\u7aef7800-1000": "#FB9276", "\u9632\u706b\u5899": "#FBCA04", "\u9e92\u9e9fV10\u7cfb\u5217": "#1D76DB", "\u9e92\u9e9fV3.3": "#0052CC"}}